PyCosimLibrary/__init__.py
PyCosimLibrary/autoinit.py
PyCosimLibrary/gauss_seidel_runner.py
PyCosimLibrary/jacobi_runner.py
PyCosimLibrary/jacobit_it_runner.py
PyCosimLibrary/loader.py
PyCosimLibrary/results.py
PyCosimLibrary/runner.py
PyCosimLibrary/scenario.py
PyCosimLibrary/virtual_fmus.py
PyCosimLibrary/double_msd/__init__.py
PyCosimLibrary/double_msd/fmus.py
PyCosimLibrary-0.0.5.dist-info/LICENSE
PyCosimLibrary-0.0.5.dist-info/METADATA
PyCosimLibrary-0.0.5.dist-info/WHEEL
PyCosimLibrary-0.0.5.dist-info/top_level.txt
PyCosimLibrary-0.0.5.dist-info/RECORD
