Metadata-Version: 2.1
Name: PyCosimLibrary
Version: 0.0.5
Summary: A co-simulation library with the most common master algorithms.
Home-page: https://github.com/clagms/PyCosimLibrary
Author: Claudio Gomes
Author-email: claudio.gomes@eng.au.dk
License: UNKNOWN
Platform: UNKNOWN
Classifier: Programming Language :: Python :: 3
Classifier: Operating System :: OS Independent
Requires-Python: >=3.6
Requires-Dist: fmpy
